{
  "case_id": "live_ca_recovery_ngos_2026_04_24",
  "citation_verification": {
    "case_id": "live_ca_recovery_ngos_2026_04_24",
    "checked_claim_count": 718,
    "checks": [],
    "created_at": "2026-05-01T13:35:23+00:00",
    "error_count": 0,
    "status": "PASS",
    "verification_id": "citation_verification_50d65ba265aadb59",
    "warning_count": 0
  },
  "files": {
    "case_dossier_json": "case_dossier.json",
    "case_dossier_markdown": "case_dossier.md",
    "index_html": "index.html",
    "source_ledger_json": "source_ledger.json"
  },
  "generated_at": "2026-05-01T13:37:21+00:00",
  "human_review_required": true,
  "link_integrity": {
    "checked_url_count": 78,
    "checks": [
      {
        "check_id": "link_check_93d8655e54e96737",
        "content_type": "text/html; charset=utf-8",
        "error": "",
        "final_url": "https://projects.propublica.org/nonprofits/organizations/954079133",
        "http_status": 200,
        "status": "PASS",
        "url": "https://projects.propublica.org/nonprofits/organizations/954079133"
      },
      {
        "check_id": "link_check_89b442b28347cea0",
        "content_type": "text/csv",
        "error": "",
        "final_url": "https://apps.irs.gov/pub/epostcard/990/xml/2024/index_2024.csv",
        "http_status": 200,
        "status": "PASS",
        "url": "https://apps.irs.gov/pub/epostcard/990/xml/2024/index_2024.csv"
      },
      {
        "check_id": "link_check_149ecf5f60b18a10",
        "content_type": "text/csv",
        "error": "",
        "final_url": "https://apps.irs.gov/pub/epostcard/990/xml/2025/index_2025.csv",
        "http_status": 200,
        "status": "PASS",
        "url": "https://apps.irs.gov/pub/epostcard/990/xml/2025/index_2025.csv"
      },
      {
        "check_id": "link_check_e551c0aad5950701",
        "content_type": "text/csv",
        "error": "",
        "final_url": "https://apps.irs.gov/pub/epostcard/990/xml/2026/index_2026.csv",
        "http_status": 200,
        "status": "PASS",
        "url": "https://apps.irs.gov/pub/epostcard/990/xml/2026/index_2026.csv"
      },
      {
        "check_id": "link_check_fc0bfa147e7b35a0",
        "content_type": "application/pdf",
        "error": "",
        "final_url": "https://s3-us-gov-west-1.amazonaws.com/cg-ac8bf271-4c6d-4ee0-bd36-1415b839a93c/singleauditreport/2016-06-CENSUS-0000119575.pdf?response-content-disposition=attachment%3Bfilename%3D2016-06-CENSUS-0000119575.pdf&X-Amz-Algorithm=AWS4-HMAC-SHA256&X-Amz-Credential=AKIAR7FXZINYPTKJO46C%2F20260501%2Fus-gov-west-1%2Fs3%2Faws4_request&X-Amz-Date=20260501T133623Z&X-Amz-Expires=30&X-Amz-SignedHeaders=host&X-Amz-Signature=9696b251a4843a235d68840019c0075505f953104abfe54f7a0943406869e135",
        "http_status": 200,
        "status": "PASS",
        "url": "https://app.fac.gov/dissemination/report/pdf/2016-06-CENSUS-0000119575"
      },
      {
        "check_id": "link_check_27e8c370bdf6039c",
        "content_type": "text/csv",
        "error": "",
        "final_url": "https://s3-us-gov-west-1.amazonaws.com/cg-ac8bf271-4c6d-4ee0-bd36-1415b839a93c/public-data/gsa/full/findings.csv?response-content-disposition=attachment%3Bfilename%3Dfindings.csv&X-Amz-Algorithm=AWS4-HMAC-SHA256&X-Amz-Credential=AKIAR7FXZINYPTKJO46C%2F20260501%2Fus-gov-west-1%2Fs3%2Faws4_request&X-Amz-Date=20260501T133624Z&X-Amz-Expires=30&X-Amz-SignedHeaders=host&X-Amz-Signature=1d7b0a412048fa6c268bdf62913439725056c74622e7994900c8dd16ed26c1fd",
        "http_status": 200,
        "status": "PASS",
        "url": "https://app.fac.gov/dissemination/public-data/gsa/full/findings.csv"
      },
      {
        "check_id": "link_check_8a8020095730e3c7",
        "content_type": "text/csv",
        "error": "",
        "final_url": "https://s3-us-gov-west-1.amazonaws.com/cg-ac8bf271-4c6d-4ee0-bd36-1415b839a93c/public-data/gsa/full/federal_awards.csv?response-content-disposition=attachment%3Bfilename%3Dfederal_awards.csv&X-Amz-Algorithm=AWS4-HMAC-SHA256&X-Amz-Credential=AKIAR7FXZINYPTKJO46C%2F20260501%2Fus-gov-west-1%2Fs3%2Faws4_request&X-Amz-Date=20260501T133624Z&X-Amz-Expires=30&X-Amz-SignedHeaders=host&X-Amz-Signature=8b60965271d52f02f9419bb9a8d2155b72821f381c21956ebd23a1c4733a386c",
        "http_status": 200,
        "status": "PASS",
        "url": "https://app.fac.gov/dissemination/public-data/gsa/full/federal_awards.csv"
      },
      {
        "check_id": "link_check_fd2f009f8d626585",
        "content_type": "text/html; charset=utf-8",
        "error": "",
        "final_url": "https://services7.arcgis.com/7MUwsS9z05YumJRZ/arcgis/rest/services/SUDS_Facilities_LCD_view/FeatureServer/7",
        "http_status": 200,
        "status": "PASS",
        "url": "https://services7.arcgis.com/7MUwsS9z05YumJRZ/arcgis/rest/services/SUDS_Facilities_LCD_view/FeatureServer/7"
      },
      {
        "check_id": "link_check_adb08c043eb5545d",
        "content_type": "text/html",
        "error": "",
        "final_url": "https://www.dhcs.ca.gov/provgovpart/SUD-LCR/Pages/SUS-REV-NOV.aspx",
        "http_status": 200,
        "status": "PASS",
        "url": "https://www.dhcs.ca.gov/provgovpart/SUD-LCR/Pages/SUS-REV-NOV.aspx"
      },
      {
        "check_id": "link_check_c25cd4f7f00b0c44",
        "content_type": "application/pdf",
        "error": "",
        "final_url": "https://file.lacounty.gov/SDSInter/auditor/cmr/1124357_2022-05-13TarzanaTreatmentCentersInc-ADepartmentofMentalHealthProgramServicesProvider-FiscalComplianceReview.pdf",
        "http_status": 200,
        "status": "PASS",
        "url": "https://file.lacounty.gov/SDSInter/auditor/cmr/1124357_2022-05-13TarzanaTreatmentCentersInc-ADepartmentofMentalHealthProgramServicesProvider-FiscalComplianceReview.pdf"
      },
      {
        "check_id": "link_check_3452d98ce8c00879",
        "content_type": "text/html",
        "error": "",
        "final_url": "https://www.dhcs.ca.gov/provgovpart/Pages/caloms-treatment.aspx",
        "http_status": 200,
        "status": "PASS",
        "url": "https://www.dhcs.ca.gov/provgovpart/Pages/caloms-treatment.aspx"
      },
      {
        "check_id": "link_check_a8ee066df49933c7",
        "content_type": "text/html",
        "error": "",
        "final_url": "https://www.dhcs.ca.gov/provgovpart/SUD-LCR/Pages/Suspension-Revocation.aspx",
        "http_status": 200,
        "status": "PASS",
        "url": "https://www.dhcs.ca.gov/provgovpart/SUD-LCR/Pages/Suspension-Revocation.aspx"
      },
      {
        "check_id": "link_check_4b3194689984c678",
        "content_type": "text/html; charset=utf-8",
        "error": "",
        "final_url": "https://data.chhs.ca.gov/dataset/county-health-status-profiles",
        "http_status": 200,
        "status": "PASS",
        "url": "https://data.chhs.ca.gov/dataset/county-health-status-profiles"
      },
      {
        "check_id": "link_check_e6db47d498fe276e",
        "content_type": "text/html; charset=utf-8",
        "error": "",
        "final_url": "https://lab.data.ca.gov/dataset/homelessness-demographics",
        "http_status": 200,
        "status": "PASS",
        "url": "https://lab.data.ca.gov/dataset/homelessness-demographics"
      },
      {
        "check_id": "link_check_8a8f921437f09695",
        "content_type": "application/pdf",
        "error": "",
        "final_url": "https://s3-us-gov-west-1.amazonaws.com/cg-ac8bf271-4c6d-4ee0-bd36-1415b839a93c/singleauditreport/2016-06-CENSUS-0000126607.pdf?response-content-disposition=attachment%3Bfilename%3D2016-06-CENSUS-0000126607.pdf&X-Amz-Algorithm=AWS4-HMAC-SHA256&X-Amz-Credential=AKIAR7FXZINYPTKJO46C%2F20260501%2Fus-gov-west-1%2Fs3%2Faws4_request&X-Amz-Date=20260501T133628Z&X-Amz-Expires=30&X-Amz-SignedHeaders=host&X-Amz-Signature=426116c4690cc041c0a957d3e10344df739572d2c8eb2a1a8017723f3048b4bb",
        "http_status": 200,
        "status": "PASS",
        "url": "https://app.fac.gov/dissemination/report/pdf/2016-06-CENSUS-0000126607"
      },
      {
        "check_id": "link_check_c8e25c30d0fcb7fa",
        "content_type": "application/pdf",
        "error": "",
        "final_url": "https://s3-us-gov-west-1.amazonaws.com/cg-ac8bf271-4c6d-4ee0-bd36-1415b839a93c/singleauditreport/2017-06-CENSUS-0000119575.pdf?response-content-disposition=attachment%3Bfilename%3D2017-06-CENSUS-0000119575.pdf&X-Amz-Algorithm=AWS4-HMAC-SHA256&X-Amz-Credential=AKIAR7FXZINYPTKJO46C%2F20260501%2Fus-gov-west-1%2Fs3%2Faws4_request&X-Amz-Date=20260501T133628Z&X-Amz-Expires=30&X-Amz-SignedHeaders=host&X-Amz-Signature=b422270ab08572b6f0e512e10d5a7e102ffc71a74fe31d6b67d47e2a5e7fc5d1",
        "http_status": 200,
        "status": "PASS",
        "url": "https://app.fac.gov/dissemination/report/pdf/2017-06-CENSUS-0000119575"
      },
      {
        "check_id": "link_check_7dc3719ac208e007",
        "content_type": "application/pdf",
        "error": "",
        "final_url": "https://s3-us-gov-west-1.amazonaws.com/cg-ac8bf271-4c6d-4ee0-bd36-1415b839a93c/singleauditreport/2017-06-CENSUS-0000126607.pdf?response-content-disposition=attachment%3Bfilename%3D2017-06-CENSUS-0000126607.pdf&X-Amz-Algorithm=AWS4-HMAC-SHA256&X-Amz-Credential=AKIAR7FXZINYPTKJO46C%2F20260501%2Fus-gov-west-1%2Fs3%2Faws4_request&X-Amz-Date=20260501T133629Z&X-Amz-Expires=30&X-Amz-SignedHeaders=host&X-Amz-Signature=60cb22ff6409848edb29897666a9d5b71397494d5398ac61617894dc171c9bba",
        "http_status": 200,
        "status": "PASS",
        "url": "https://app.fac.gov/dissemination/report/pdf/2017-06-CENSUS-0000126607"
      },
      {
        "check_id": "link_check_a748647684cab868",
        "content_type": "application/pdf",
        "error": "",
        "final_url": "https://s3-us-gov-west-1.amazonaws.com/cg-ac8bf271-4c6d-4ee0-bd36-1415b839a93c/singleauditreport/2018-06-CENSUS-0000119575.pdf?response-content-disposition=attachment%3Bfilename%3D2018-06-CENSUS-0000119575.pdf&X-Amz-Algorithm=AWS4-HMAC-SHA256&X-Amz-Credential=AKIAR7FXZINYPTKJO46C%2F20260501%2Fus-gov-west-1%2Fs3%2Faws4_request&X-Amz-Date=20260501T133630Z&X-Amz-Expires=30&X-Amz-SignedHeaders=host&X-Amz-Signature=90648a1ac1db35f356c4eb63db7c62984f9c0a291bc93c8b10f3850950496e6b",
        "http_status": 200,
        "status": "PASS",
        "url": "https://app.fac.gov/dissemination/report/pdf/2018-06-CENSUS-0000119575"
      },
      {
        "check_id": "link_check_24197dda6fcaea6d",
        "content_type": "application/pdf",
        "error": "",
        "final_url": "https://s3-us-gov-west-1.amazonaws.com/cg-ac8bf271-4c6d-4ee0-bd36-1415b839a93c/singleauditreport/2018-06-CENSUS-0000126607.pdf?response-content-disposition=attachment%3Bfilename%3D2018-06-CENSUS-0000126607.pdf&X-Amz-Algorithm=AWS4-HMAC-SHA256&X-Amz-Credential=AKIAR7FXZINYPTKJO46C%2F20260501%2Fus-gov-west-1%2Fs3%2Faws4_request&X-Amz-Date=20260501T133631Z&X-Amz-Expires=30&X-Amz-SignedHeaders=host&X-Amz-Signature=5ac766defcfadd79ddcbd71e342732fe6fd8d3eb7591cd1307692a227e2db23d",
        "http_status": 200,
        "status": "PASS",
        "url": "https://app.fac.gov/dissemination/report/pdf/2018-06-CENSUS-0000126607"
      },
      {
        "check_id": "link_check_eccb2a8d8591db7b",
        "content_type": "application/pdf",
        "error": "",
        "final_url": "https://s3-us-gov-west-1.amazonaws.com/cg-ac8bf271-4c6d-4ee0-bd36-1415b839a93c/singleauditreport/2019-06-CENSUS-0000119575.pdf?response-content-disposition=attachment%3Bfilename%3D2019-06-CENSUS-0000119575.pdf&X-Amz-Algorithm=AWS4-HMAC-SHA256&X-Amz-Credential=AKIAR7FXZINYPTKJO46C%2F20260501%2Fus-gov-west-1%2Fs3%2Faws4_request&X-Amz-Date=20260501T133632Z&X-Amz-Expires=30&X-Amz-SignedHeaders=host&X-Amz-Signature=21d7d328e11bf23cf49ed36f559a8d1810e12913184bdc1791761818f73ece35",
        "http_status": 200,
        "status": "PASS",
        "url": "https://app.fac.gov/dissemination/report/pdf/2019-06-CENSUS-0000119575"
      },
      {
        "check_id": "link_check_5783bf3a2ceb43e0",
        "content_type": "application/pdf",
        "error": "",
        "final_url": "https://s3-us-gov-west-1.amazonaws.com/cg-ac8bf271-4c6d-4ee0-bd36-1415b839a93c/singleauditreport/2019-06-CENSUS-0000126607.pdf?response-content-disposition=attachment%3Bfilename%3D2019-06-CENSUS-0000126607.pdf&X-Amz-Algorithm=AWS4-HMAC-SHA256&X-Amz-Credential=AKIAR7FXZINYPTKJO46C%2F20260501%2Fus-gov-west-1%2Fs3%2Faws4_request&X-Amz-Date=20260501T133633Z&X-Amz-Expires=30&X-Amz-SignedHeaders=host&X-Amz-Signature=09d602bf677ae37c03fb2a98ef5429dc2920e7be861df8e59263a87a41680f19",
        "http_status": 200,
        "status": "PASS",
        "url": "https://app.fac.gov/dissemination/report/pdf/2019-06-CENSUS-0000126607"
      },
      {
        "check_id": "link_check_517084c8066e81f8",
        "content_type": "application/pdf",
        "error": "",
        "final_url": "https://s3-us-gov-west-1.amazonaws.com/cg-ac8bf271-4c6d-4ee0-bd36-1415b839a93c/singleauditreport/2020-06-CENSUS-0000119575.pdf?response-content-disposition=attachment%3Bfilename%3D2020-06-CENSUS-0000119575.pdf&X-Amz-Algorithm=AWS4-HMAC-SHA256&X-Amz-Credential=AKIAR7FXZINYPTKJO46C%2F20260501%2Fus-gov-west-1%2Fs3%2Faws4_request&X-Amz-Date=20260501T133634Z&X-Amz-Expires=30&X-Amz-SignedHeaders=host&X-Amz-Signature=6d89a118d0fb52de85a8d486d1f9b1b4149c873f113ab5697d0fc7e6b6c6e089",
        "http_status": 200,
        "status": "PASS",
        "url": "https://app.fac.gov/dissemination/report/pdf/2020-06-CENSUS-0000119575"
      },
      {
        "check_id": "link_check_2ee39e06701dea87",
        "content_type": "application/pdf",
        "error": "",
        "final_url": "https://s3-us-gov-west-1.amazonaws.com/cg-ac8bf271-4c6d-4ee0-bd36-1415b839a93c/singleauditreport/2020-06-CENSUS-0000126607.pdf?response-content-disposition=attachment%3Bfilename%3D2020-06-CENSUS-0000126607.pdf&X-Amz-Algorithm=AWS4-HMAC-SHA256&X-Amz-Credential=AKIAR7FXZINYPTKJO46C%2F20260501%2Fus-gov-west-1%2Fs3%2Faws4_request&X-Amz-Date=20260501T133635Z&X-Amz-Expires=30&X-Amz-SignedHeaders=host&X-Amz-Signature=33eb1253d9e344b0ae873316cf7c150fccd10d62b67d46c4432326815752d0d2",
        "http_status": 200,
        "status": "PASS",
        "url": "https://app.fac.gov/dissemination/report/pdf/2020-06-CENSUS-0000126607"
      },
      {
        "check_id": "link_check_6d792db933a0a3df",
        "content_type": "application/pdf",
        "error": "",
        "final_url": "https://s3-us-gov-west-1.amazonaws.com/cg-ac8bf271-4c6d-4ee0-bd36-1415b839a93c/singleauditreport/2021-06-CENSUS-0000119575.pdf?response-content-disposition=attachment%3Bfilename%3D2021-06-CENSUS-0000119575.pdf&X-Amz-Algorithm=AWS4-HMAC-SHA256&X-Amz-Credential=AKIAR7FXZINYPTKJO46C%2F20260501%2Fus-gov-west-1%2Fs3%2Faws4_request&X-Amz-Date=20260501T133636Z&X-Amz-Expires=30&X-Amz-SignedHeaders=host&X-Amz-Signature=b52f73f52d8e67f6a8ee3b859d8776e9c4d0405d52862f1717f2ccb4d847a20c",
        "http_status": 200,
        "status": "PASS",
        "url": "https://app.fac.gov/dissemination/report/pdf/2021-06-CENSUS-0000119575"
      },
      {
        "check_id": "link_check_ccb79ab093d08182",
        "content_type": "application/pdf",
        "error": "",
        "final_url": "https://s3-us-gov-west-1.amazonaws.com/cg-ac8bf271-4c6d-4ee0-bd36-1415b839a93c/singleauditreport/2021-06-CENSUS-0000126607.pdf?response-content-disposition=attachment%3Bfilename%3D2021-06-CENSUS-0000126607.pdf&X-Amz-Algorithm=AWS4-HMAC-SHA256&X-Amz-Credential=AKIAR7FXZINYPTKJO46C%2F20260501%2Fus-gov-west-1%2Fs3%2Faws4_request&X-Amz-Date=20260501T133637Z&X-Amz-Expires=30&X-Amz-SignedHeaders=host&X-Amz-Signature=b41be58778114c0b97865abf39fce7df711d240434d26be2789419b87ab62630",
        "http_status": 200,
        "status": "PASS",
        "url": "https://app.fac.gov/dissemination/report/pdf/2021-06-CENSUS-0000126607"
      },
      {
        "check_id": "link_check_a26eedca1f231536",
        "content_type": "application/pdf",
        "error": "",
        "final_url": "https://s3-us-gov-west-1.amazonaws.com/cg-ac8bf271-4c6d-4ee0-bd36-1415b839a93c/singleauditreport/2022-06-CENSUS-0000119575.pdf?response-content-disposition=attachment%3Bfilename%3D2022-06-CENSUS-0000119575.pdf&X-Amz-Algorithm=AWS4-HMAC-SHA256&X-Amz-Credential=AKIAR7FXZINYPTKJO46C%2F20260501%2Fus-gov-west-1%2Fs3%2Faws4_request&X-Amz-Date=20260501T133638Z&X-Amz-Expires=30&X-Amz-SignedHeaders=host&X-Amz-Signature=69a27365c43cf576b3ab336c28ba1c142884ef0c13e9fa690a236e401c2b269e",
        "http_status": 200,
        "status": "PASS",
        "url": "https://app.fac.gov/dissemination/report/pdf/2022-06-CENSUS-0000119575"
      },
      {
        "check_id": "link_check_e2f8fc025ee41576",
        "content_type": "application/pdf",
        "error": "",
        "final_url": "https://s3-us-gov-west-1.amazonaws.com/cg-ac8bf271-4c6d-4ee0-bd36-1415b839a93c/singleauditreport/2023-06-GSAFAC-0000019151.pdf?response-content-disposition=attachment%3Bfilename%3D2023-06-GSAFAC-0000019151.pdf&X-Amz-Algorithm=AWS4-HMAC-SHA256&X-Amz-Credential=AKIAR7FXZINYPTKJO46C%2F20260501%2Fus-gov-west-1%2Fs3%2Faws4_request&X-Amz-Date=20260501T133639Z&X-Amz-Expires=30&X-Amz-SignedHeaders=host&X-Amz-Signature=aeab42f410c359650f8f3159aeda7cb113026c4b1691989be7910dcaaf8748ef",
        "http_status": 200,
        "status": "PASS",
        "url": "https://app.fac.gov/dissemination/report/pdf/2023-06-GSAFAC-0000019151"
      },
      {
        "check_id": "link_check_9ada5f190020e194",
        "content_type": "application/pdf",
        "error": "",
        "final_url": "https://s3-us-gov-west-1.amazonaws.com/cg-ac8bf271-4c6d-4ee0-bd36-1415b839a93c/singleauditreport/2023-06-GSAFAC-0000031913.pdf?response-content-disposition=attachment%3Bfilename%3D2023-06-GSAFAC-0000031913.pdf&X-Amz-Algorithm=AWS4-HMAC-SHA256&X-Amz-Credential=AKIAR7FXZINYPTKJO46C%2F20260501%2Fus-gov-west-1%2Fs3%2Faws4_request&X-Amz-Date=20260501T133640Z&X-Amz-Expires=30&X-Amz-SignedHeaders=host&X-Amz-Signature=f748fd0b926119675c956f887b68a72d35fdc0dfa2905c66a1633c9f300e70b6",
        "http_status": 200,
        "status": "PASS",
        "url": "https://app.fac.gov/dissemination/report/pdf/2023-06-GSAFAC-0000031913"
      },
      {
        "check_id": "link_check_6f5171559bba1d97",
        "content_type": "application/pdf",
        "error": "",
        "final_url": "https://s3-us-gov-west-1.amazonaws.com/cg-ac8bf271-4c6d-4ee0-bd36-1415b839a93c/singleauditreport/2024-06-GSAFAC-0000354996.pdf?response-content-disposition=attachment%3Bfilename%3D2024-06-GSAFAC-0000354996.pdf&X-Amz-Algorithm=AWS4-HMAC-SHA256&X-Amz-Credential=AKIAR7FXZINYPTKJO46C%2F20260501%2Fus-gov-west-1%2Fs3%2Faws4_request&X-Amz-Date=20260501T133641Z&X-Amz-Expires=30&X-Amz-SignedHeaders=host&X-Amz-Signature=d8262ec9a6045742508c57db22e241bb628aea2408362823c85bd566602ca6b8",
        "http_status": 200,
        "status": "PASS",
        "url": "https://app.fac.gov/dissemination/report/pdf/2024-06-GSAFAC-0000354996"
      },
      {
        "check_id": "link_check_77b9fc351938f3fc",
        "content_type": "application/pdf",
        "error": "",
        "final_url": "https://s3-us-gov-west-1.amazonaws.com/cg-ac8bf271-4c6d-4ee0-bd36-1415b839a93c/singleauditreport/2024-06-GSAFAC-0000360511.pdf?response-content-disposition=attachment%3Bfilename%3D2024-06-GSAFAC-0000360511.pdf&X-Amz-Algorithm=AWS4-HMAC-SHA256&X-Amz-Credential=AKIAR7FXZINYPTKJO46C%2F20260501%2Fus-gov-west-1%2Fs3%2Faws4_request&X-Amz-Date=20260501T133642Z&X-Amz-Expires=30&X-Amz-SignedHeaders=host&X-Amz-Signature=a3d146a77b4d8ced4200d555144c75574aebd53b51cd7cbefa38de416c91064d",
        "http_status": 200,
        "status": "PASS",
        "url": "https://app.fac.gov/dissemination/report/pdf/2024-06-GSAFAC-0000360511"
      },
      {
        "check_id": "link_check_34659488b9392148",
        "content_type": "application/pdf",
        "error": "",
        "final_url": "https://s3-us-gov-west-1.amazonaws.com/cg-ac8bf271-4c6d-4ee0-bd36-1415b839a93c/singleauditreport/2025-06-GSAFAC-0000405366.pdf?response-content-disposition=attachment%3Bfilename%3D2025-06-GSAFAC-0000405366.pdf&X-Amz-Algorithm=AWS4-HMAC-SHA256&X-Amz-Credential=AKIAR7FXZINYPTKJO46C%2F20260501%2Fus-gov-west-1%2Fs3%2Faws4_request&X-Amz-Date=20260501T133643Z&X-Amz-Expires=30&X-Amz-SignedHeaders=host&X-Amz-Signature=8de34aa95b9905ed0895154ae08347c84c0dc248347ace4ed191bcfddf3d082e",
        "http_status": 200,
        "status": "PASS",
        "url": "https://app.fac.gov/dissemination/report/pdf/2025-06-GSAFAC-0000405366"
      },
      {
        "check_id": "link_check_dc4e28e60f975ab1",
        "content_type": "application/pdf",
        "error": "",
        "final_url": "https://s3-us-gov-west-1.amazonaws.com/cg-ac8bf271-4c6d-4ee0-bd36-1415b839a93c/singleauditreport/2025-06-GSAFAC-0000408150.pdf?response-content-disposition=attachment%3Bfilename%3D2025-06-GSAFAC-0000408150.pdf&X-Amz-Algorithm=AWS4-HMAC-SHA256&X-Amz-Credential=AKIAR7FXZINYPTKJO46C%2F20260501%2Fus-gov-west-1%2Fs3%2Faws4_request&X-Amz-Date=20260501T133644Z&X-Amz-Expires=30&X-Amz-SignedHeaders=host&X-Amz-Signature=ef86fee398517289c31992bf971661fc4893534689cee4dc90d995aef2229687",
        "http_status": 200,
        "status": "PASS",
        "url": "https://app.fac.gov/dissemination/report/pdf/2025-06-GSAFAC-0000408150"
      },
      {
        "check_id": "link_check_7c5af7c49411d1e1",
        "content_type": "application/pdf",
        "error": "",
        "final_url": "https://s3-us-gov-west-1.amazonaws.com/cg-ac8bf271-4c6d-4ee0-bd36-1415b839a93c/singleauditreport/2016-06-CENSUS-0000122774.pdf?response-content-disposition=attachment%3Bfilename%3D2016-06-CENSUS-0000122774.pdf&X-Amz-Algorithm=AWS4-HMAC-SHA256&X-Amz-Credential=AKIAR7FXZINYPTKJO46C%2F20260501%2Fus-gov-west-1%2Fs3%2Faws4_request&X-Amz-Date=20260501T133645Z&X-Amz-Expires=30&X-Amz-SignedHeaders=host&X-Amz-Signature=81a7555e02bb48007c9538617620d86930c501b19e831f46415d642325b313cd",
        "http_status": 200,
        "status": "PASS",
        "url": "https://app.fac.gov/dissemination/report/pdf/2016-06-CENSUS-0000122774"
      },
      {
        "check_id": "link_check_7c9ea293da872f23",
        "content_type": "application/pdf",
        "error": "",
        "final_url": "https://s3-us-gov-west-1.amazonaws.com/cg-ac8bf271-4c6d-4ee0-bd36-1415b839a93c/singleauditreport/2016-06-CENSUS-0000124840.pdf?response-content-disposition=attachment%3Bfilename%3D2016-06-CENSUS-0000124840.pdf&X-Amz-Algorithm=AWS4-HMAC-SHA256&X-Amz-Credential=AKIAR7FXZINYPTKJO46C%2F20260501%2Fus-gov-west-1%2Fs3%2Faws4_request&X-Amz-Date=20260501T133646Z&X-Amz-Expires=30&X-Amz-SignedHeaders=host&X-Amz-Signature=c6893cdf6c26dc153110c7d05505da8073c4ef07c38a66f073d1a5c353c15130",
        "http_status": 200,
        "status": "PASS",
        "url": "https://app.fac.gov/dissemination/report/pdf/2016-06-CENSUS-0000124840"
      },
      {
        "check_id": "link_check_8e8ebaa32509cf4c",
        "content_type": "application/pdf",
        "error": "",
        "final_url": "https://s3-us-gov-west-1.amazonaws.com/cg-ac8bf271-4c6d-4ee0-bd36-1415b839a93c/singleauditreport/2016-06-CENSUS-0000124927.pdf?response-content-disposition=attachment%3Bfilename%3D2016-06-CENSUS-0000124927.pdf&X-Amz-Algorithm=AWS4-HMAC-SHA256&X-Amz-Credential=AKIAR7FXZINYPTKJO46C%2F20260501%2Fus-gov-west-1%2Fs3%2Faws4_request&X-Amz-Date=20260501T133647Z&X-Amz-Expires=30&X-Amz-SignedHeaders=host&X-Amz-Signature=bfaa99f19af4fb18c3fc0f49fd188a6eb8ee655ec62d1d6a603d96aa78101864",
        "http_status": 200,
        "status": "PASS",
        "url": "https://app.fac.gov/dissemination/report/pdf/2016-06-CENSUS-0000124927"
      },
      {
        "check_id": "link_check_94b298a6686cc765",
        "content_type": "application/pdf",
        "error": "",
        "final_url": "https://s3-us-gov-west-1.amazonaws.com/cg-ac8bf271-4c6d-4ee0-bd36-1415b839a93c/singleauditreport/2016-06-CENSUS-0000246480.pdf?response-content-disposition=attachment%3Bfilename%3D2016-06-CENSUS-0000246480.pdf&X-Amz-Algorithm=AWS4-HMAC-SHA256&X-Amz-Credential=AKIAR7FXZINYPTKJO46C%2F20260501%2Fus-gov-west-1%2Fs3%2Faws4_request&X-Amz-Date=20260501T133648Z&X-Amz-Expires=30&X-Amz-SignedHeaders=host&X-Amz-Signature=41acc8b91df59f1a97f7dc4f603232e92eee38660472a3b79aca14887f849bad",
        "http_status": 200,
        "status": "PASS",
        "url": "https://app.fac.gov/dissemination/report/pdf/2016-06-CENSUS-0000246480"
      },
      {
        "check_id": "link_check_aa0070a48a11680b",
        "content_type": "application/pdf",
        "error": "",
        "final_url": "https://s3-us-gov-west-1.amazonaws.com/cg-ac8bf271-4c6d-4ee0-bd36-1415b839a93c/singleauditreport/2017-06-CENSUS-0000122774.pdf?response-content-disposition=attachment%3Bfilename%3D2017-06-CENSUS-0000122774.pdf&X-Amz-Algorithm=AWS4-HMAC-SHA256&X-Amz-Credential=AKIAR7FXZINYPTKJO46C%2F20260501%2Fus-gov-west-1%2Fs3%2Faws4_request&X-Amz-Date=20260501T133649Z&X-Amz-Expires=30&X-Amz-SignedHeaders=host&X-Amz-Signature=ca5660c5c9441760cec2f19daa2668ee4c0d08bdb144156a5ace23375de35554",
        "http_status": 200,
        "status": "PASS",
        "url": "https://app.fac.gov/dissemination/report/pdf/2017-06-CENSUS-0000122774"
      },
      {
        "check_id": "link_check_7a32536e66b6e292",
        "content_type": "application/pdf",
        "error": "",
        "final_url": "https://s3-us-gov-west-1.amazonaws.com/cg-ac8bf271-4c6d-4ee0-bd36-1415b839a93c/singleauditreport/2017-06-CENSUS-0000124840.pdf?response-content-disposition=attachment%3Bfilename%3D2017-06-CENSUS-0000124840.pdf&X-Amz-Algorithm=AWS4-HMAC-SHA256&X-Amz-Credential=AKIAR7FXZINYPTKJO46C%2F20260501%2Fus-gov-west-1%2Fs3%2Faws4_request&X-Amz-Date=20260501T133650Z&X-Amz-Expires=30&X-Amz-SignedHeaders=host&X-Amz-Signature=be2dcf6fa20a6f81ac02e61c1e6ef5797f42b24da8b5dd11e29f978370706fc8",
        "http_status": 200,
        "status": "PASS",
        "url": "https://app.fac.gov/dissemination/report/pdf/2017-06-CENSUS-0000124840"
      },
      {
        "check_id": "link_check_dab22ed61699268b",
        "content_type": "application/pdf",
        "error": "",
        "final_url": "https://s3-us-gov-west-1.amazonaws.com/cg-ac8bf271-4c6d-4ee0-bd36-1415b839a93c/singleauditreport/2017-06-CENSUS-0000124927.pdf?response-content-disposition=attachment%3Bfilename%3D2017-06-CENSUS-0000124927.pdf&X-Amz-Algorithm=AWS4-HMAC-SHA256&X-Amz-Credential=AKIAR7FXZINYPTKJO46C%2F20260501%2Fus-gov-west-1%2Fs3%2Faws4_request&X-Amz-Date=20260501T133651Z&X-Amz-Expires=30&X-Amz-SignedHeaders=host&X-Amz-Signature=56dd6996e2a70d2ab589d41b9d477924bbe1ffb8d8a79ee357244639254010de",
        "http_status": 200,
        "status": "PASS",
        "url": "https://app.fac.gov/dissemination/report/pdf/2017-06-CENSUS-0000124927"
      },
      {
        "check_id": "link_check_1f72cd96ddf0e001",
        "content_type": "text/html; charset=UTF-8",
        "error": "",
        "final_url": "https://www.healthright360.org/our-services/substance-use-disorder/",
        "http_status": 200,
        "status": "PASS",
        "url": "https://www.healthright360.org/our-services/substance-use-disorder/"
      },
      {
        "check_id": "link_check_2cbee6147a858a1c",
        "content_type": "text/html; charset=utf-8",
        "error": "",
        "final_url": "https://data.chhs.ca.gov/",
        "http_status": 200,
        "status": "PASS",
        "url": "https://data.chhs.ca.gov/"
      },
      {
        "check_id": "link_check_3568cae02dbd6e0e",
        "content_type": "text/html; charset=utf-8",
        "error": "",
        "final_url": "https://lab.data.ca.gov/",
        "http_status": 200,
        "status": "PASS",
        "url": "https://lab.data.ca.gov/"
      },
      {
        "check_id": "link_check_7f5608f0d5e0b908",
        "content_type": "text/html; charset=utf-8",
        "error": "",
        "final_url": "https://lab.data.ca.gov/dataset/ca-system-performance-measures-statewide-and-by-coc",
        "http_status": 200,
        "status": "PASS",
        "url": "https://lab.data.ca.gov/dataset/ca-system-performance-measures-statewide-and-by-coc"
      },
      {
        "check_id": "link_check_38095c3c6ea2faa9",
        "content_type": "text/html; charset=utf-8",
        "error": "",
        "final_url": "https://lab.data.ca.gov/dataset/medication-assisted-treatment-in-medi-cal-for-opioid-use-disorders-by-county",
        "http_status": 200,
        "status": "PASS",
        "url": "https://lab.data.ca.gov/dataset/medication-assisted-treatment-in-medi-cal-for-opioid-use-disorders-by-county"
      },
      {
        "check_id": "link_check_0202dab06d22700e",
        "content_type": "text/csv",
        "error": "",
        "final_url": "https://data-openjustice.doj.ca.gov/sites/default/files/dataset/2025-07/Crimes_and_Clearances_with_Arson-1985-2024.csv",
        "http_status": 200,
        "status": "PASS",
        "url": "https://data-openjustice.doj.ca.gov/sites/default/files/dataset/2025-07/Crimes_and_Clearances_with_Arson-1985-2024.csv"
      },
      {
        "check_id": "link_check_7cefe6131ae2652e",
        "content_type": "text/html; charset=UTF-8",
        "error": "",
        "final_url": "https://www.tarzanatc.org/who-we-are/meet-us/",
        "http_status": 200,
        "status": "PASS",
        "url": "https://www.tarzanatc.org/who-we-are/meet-us/"
      },
      {
        "check_id": "link_check_490381e74bf9449c",
        "content_type": "text/html; charset=UTF-8",
        "error": "",
        "final_url": "https://www.tarzanatc.org/who-we-are/our-history/",
        "http_status": 200,
        "status": "PASS",
        "url": "https://www.tarzanatc.org/who-we-are/our-history/"
      },
      {
        "check_id": "link_check_4e84b287598ae02c",
        "content_type": "text/html; charset=UTF-8",
        "error": "",
        "final_url": "https://www.tarzanatc.org/treatment-news/",
        "http_status": 200,
        "status": "PASS",
        "url": "https://www.tarzanatc.org/treatment-news/"
      },
      {
        "check_id": "link_check_6e126217f1dc9c16",
        "content_type": "text/html; charset=UTF-8",
        "error": "",
        "final_url": "https://www.healthright360.org/about/staff-and-board/",
        "http_status": 200,
        "status": "PASS",
        "url": "https://www.healthright360.org/about/staff-and-board/"
      },
      {
        "check_id": "link_check_263ff02f8d6d3068",
        "content_type": "text/html; charset=UTF-8",
        "error": "",
        "final_url": "https://www.healthright360.org/about/news/",
        "http_status": 200,
        "status": "PASS",
        "url": "https://www.healthright360.org/about/news/"
      },
      {
        "check_id": "link_check_c76875eb21f50349",
        "content_type": "text/html; charset=UTF-8",
        "error": "",
        "final_url": "https://www.healthright360.org/about/news/",
        "http_status": 200,
        "status": "PASS",
        "url": "https://www.healthright360.org/about/news"
      },
      {
        "check_id": "link_check_9fff15d15b9d68e7",
        "content_type": "text/html; charset=UTF-8",
        "error": "",
        "final_url": "https://www.healthright360.org/about/our-impact/",
        "http_status": 200,
        "status": "PASS",
        "url": "https://www.healthright360.org/about/our-impact/"
      },
      {
        "check_id": "link_check_82ad7f236ec5a0c8",
        "content_type": "text/html; charset=UTF-8",
        "error": "",
        "final_url": "https://westcare.com/leadership/",
        "http_status": 200,
        "status": "PASS",
        "url": "https://westcare.com/leadership/"
      },
      {
        "check_id": "link_check_d9d9a6054d28461e",
        "content_type": "text/html; charset=UTF-8",
        "error": "",
        "final_url": "https://westcare.com/leadership/senior/",
        "http_status": 200,
        "status": "PASS",
        "url": "https://westcare.com/leadership/senior/"
      },
      {
        "check_id": "link_check_293d170bb98efe41",
        "content_type": "text/html; charset=UTF-8",
        "error": "",
        "final_url": "https://westcare.com/express/",
        "http_status": 200,
        "status": "PASS",
        "url": "https://westcare.com/express/"
      },
      {
        "check_id": "link_check_7a9d26bd4b7a7b92",
        "content_type": "text/html; charset=UTF-8",
        "error": "",
        "final_url": "https://westcare.com/impact-report/",
        "http_status": 200,
        "status": "PASS",
        "url": "https://westcare.com/impact-report/"
      },
      {
        "check_id": "link_check_edaf8deaa6c517a4",
        "content_type": "text/html; charset=UTF-8",
        "error": "",
        "final_url": "https://bhs-inc.org/",
        "http_status": 200,
        "status": "PASS",
        "url": "https://bhs-inc.org/"
      },
      {
        "check_id": "link_check_b4b25e70e9f6e0e8",
        "content_type": "text/html; charset=UTF-8",
        "error": "",
        "final_url": "https://www.bhs-inc.org/about-us",
        "http_status": 200,
        "status": "PASS",
        "url": "https://www.bhs-inc.org/about-us"
      },
      {
        "check_id": "link_check_4970d1941e8a76b7",
        "content_type": "text/html; charset=UTF-8",
        "error": "",
        "final_url": "https://bhs-inc.org/services",
        "http_status": 200,
        "status": "PASS",
        "url": "https://bhs-inc.org/services"
      },
      {
        "check_id": "link_check_e997847e787927d6",
        "content_type": "text/html; charset=UTF-8",
        "error": "",
        "final_url": "https://bhs-inc.org/services",
        "http_status": 200,
        "status": "PASS",
        "url": "https://bhs-inc.org/services/"
      },
      {
        "check_id": "link_check_e02d1a247d1ccbcd",
        "content_type": "text/html; charset=UTF-8",
        "error": "",
        "final_url": "https://cri-help.org/news-events/newsroom.html",
        "http_status": 200,
        "status": "PASS",
        "url": "https://cri-help.org/news-events/newsroom.html"
      },
      {
        "check_id": "link_check_d3b68998aacd6a8a",
        "content_type": "text/html; charset=UTF-8",
        "error": "",
        "final_url": "https://cri-help.org/who-we-are/core-values.html",
        "http_status": 200,
        "status": "PASS",
        "url": "https://cri-help.org/who-we-are/core-values.html"
      },
      {
        "check_id": "link_check_2b79580b844d7e22",
        "content_type": "text/html; charset=UTF-8",
        "error": "",
        "final_url": "https://cri-help.org/",
        "http_status": 200,
        "status": "PASS",
        "url": "https://cri-help.org/"
      },
      {
        "check_id": "link_check_d7a3ba62114c2c77",
        "content_type": "text/html; charset=UTF-8",
        "error": "",
        "final_url": "https://socialmodelrecovery.org/",
        "http_status": 200,
        "status": "PASS",
        "url": "https://socialmodelrecovery.org/"
      },
      {
        "check_id": "link_check_76544172f06b1bb7",
        "content_type": "text/html; charset=UTF-8",
        "error": "",
        "final_url": "https://socialmodelrecovery.org/services/",
        "http_status": 200,
        "status": "PASS",
        "url": "https://socialmodelrecovery.org/services/"
      },
      {
        "check_id": "link_check_57617484970413cc",
        "content_type": "text/html; charset=utf-8",
        "error": "",
        "final_url": "https://phoenixhouseca.org/measuring-our-impact/",
        "http_status": 200,
        "status": "PASS",
        "url": "https://phoenixhouseca.org/measuring-our-impact/"
      },
      {
        "check_id": "link_check_df1d35ae2ae85f37",
        "content_type": "text/html; charset=utf-8",
        "error": "",
        "final_url": "https://phoenixhouseca.org/annual-reports/",
        "http_status": 200,
        "status": "PASS",
        "url": "https://phoenixhouseca.org/annual-reports/"
      },
      {
        "check_id": "link_check_291099f0f0059848",
        "content_type": "text/html; charset=utf-8",
        "error": "",
        "final_url": "https://phoenixhouseca.org/impact-annual-reports/",
        "http_status": 200,
        "status": "PASS",
        "url": "https://phoenixhouseca.org/impact-annual-reports/"
      },
      {
        "check_id": "link_check_8896c7c8c46e5621",
        "content_type": "application/pdf",
        "error": "",
        "final_url": "https://s3-us-gov-west-1.amazonaws.com/cg-ac8bf271-4c6d-4ee0-bd36-1415b839a93c/singleauditreport/2018-06-CENSUS-0000122774.pdf?response-content-disposition=attachment%3Bfilename%3D2018-06-CENSUS-0000122774.pdf&X-Amz-Algorithm=AWS4-HMAC-SHA256&X-Amz-Credential=AKIAR7FXZINYPTKJO46C%2F20260501%2Fus-gov-west-1%2Fs3%2Faws4_request&X-Amz-Date=20260501T133711Z&X-Amz-Expires=30&X-Amz-SignedHeaders=host&X-Amz-Signature=72284af1f7c69c72aeac38787225960a15e8ef0bfb7f23474c204f5f882fd5f0",
        "http_status": 200,
        "status": "PASS",
        "url": "https://app.fac.gov/dissemination/report/pdf/2018-06-CENSUS-0000122774"
      },
      {
        "check_id": "link_check_0fd709bd0e3a5194",
        "content_type": "application/pdf",
        "error": "",
        "final_url": "https://s3-us-gov-west-1.amazonaws.com/cg-ac8bf271-4c6d-4ee0-bd36-1415b839a93c/singleauditreport/2018-06-CENSUS-0000124840.pdf?response-content-disposition=attachment%3Bfilename%3D2018-06-CENSUS-0000124840.pdf&X-Amz-Algorithm=AWS4-HMAC-SHA256&X-Amz-Credential=AKIAR7FXZINYPTKJO46C%2F20260501%2Fus-gov-west-1%2Fs3%2Faws4_request&X-Amz-Date=20260501T133712Z&X-Amz-Expires=30&X-Amz-SignedHeaders=host&X-Amz-Signature=4035cf788bf70ef28ca1926c89fb7f64f7f52bc4a55974d51ae5d919d16ca643",
        "http_status": 200,
        "status": "PASS",
        "url": "https://app.fac.gov/dissemination/report/pdf/2018-06-CENSUS-0000124840"
      },
      {
        "check_id": "link_check_7f74f11b27934ad1",
        "content_type": "application/pdf",
        "error": "",
        "final_url": "https://s3-us-gov-west-1.amazonaws.com/cg-ac8bf271-4c6d-4ee0-bd36-1415b839a93c/singleauditreport/2018-06-CENSUS-0000124927.pdf?response-content-disposition=attachment%3Bfilename%3D2018-06-CENSUS-0000124927.pdf&X-Amz-Algorithm=AWS4-HMAC-SHA256&X-Amz-Credential=AKIAR7FXZINYPTKJO46C%2F20260501%2Fus-gov-west-1%2Fs3%2Faws4_request&X-Amz-Date=20260501T133713Z&X-Amz-Expires=30&X-Amz-SignedHeaders=host&X-Amz-Signature=fbd91df45d2766ba887a7d1a1e6e199bf27985aba1b57318751d808780e36767",
        "http_status": 200,
        "status": "PASS",
        "url": "https://app.fac.gov/dissemination/report/pdf/2018-06-CENSUS-0000124927"
      },
      {
        "check_id": "link_check_04da17a6ab001c73",
        "content_type": "application/pdf",
        "error": "",
        "final_url": "https://s3-us-gov-west-1.amazonaws.com/cg-ac8bf271-4c6d-4ee0-bd36-1415b839a93c/singleauditreport/2018-06-CENSUS-0000247998.pdf?response-content-disposition=attachment%3Bfilename%3D2018-06-CENSUS-0000247998.pdf&X-Amz-Algorithm=AWS4-HMAC-SHA256&X-Amz-Credential=AKIAR7FXZINYPTKJO46C%2F20260501%2Fus-gov-west-1%2Fs3%2Faws4_request&X-Amz-Date=20260501T133714Z&X-Amz-Expires=30&X-Amz-SignedHeaders=host&X-Amz-Signature=e12a9a9ee112569091c3be85caed9f70672ea9a8cea3b75287a8b6f80a450d31",
        "http_status": 200,
        "status": "PASS",
        "url": "https://app.fac.gov/dissemination/report/pdf/2018-06-CENSUS-0000247998"
      },
      {
        "check_id": "link_check_c25e5dea011a4bd9",
        "content_type": "application/pdf",
        "error": "",
        "final_url": "https://s3-us-gov-west-1.amazonaws.com/cg-ac8bf271-4c6d-4ee0-bd36-1415b839a93c/singleauditreport/2019-06-CENSUS-0000122774.pdf?response-content-disposition=attachment%3Bfilename%3D2019-06-CENSUS-0000122774.pdf&X-Amz-Algorithm=AWS4-HMAC-SHA256&X-Amz-Credential=AKIAR7FXZINYPTKJO46C%2F20260501%2Fus-gov-west-1%2Fs3%2Faws4_request&X-Amz-Date=20260501T133715Z&X-Amz-Expires=30&X-Amz-SignedHeaders=host&X-Amz-Signature=e6e13ef9d54d379d453f5f0e0d15c13393e0d67dbc48c193cb922732d31fb327",
        "http_status": 200,
        "status": "PASS",
        "url": "https://app.fac.gov/dissemination/report/pdf/2019-06-CENSUS-0000122774"
      },
      {
        "check_id": "link_check_f85b51ac85918076",
        "content_type": "application/pdf",
        "error": "",
        "final_url": "https://s3-us-gov-west-1.amazonaws.com/cg-ac8bf271-4c6d-4ee0-bd36-1415b839a93c/singleauditreport/2019-06-CENSUS-0000124840.pdf?response-content-disposition=attachment%3Bfilename%3D2019-06-CENSUS-0000124840.pdf&X-Amz-Algorithm=AWS4-HMAC-SHA256&X-Amz-Credential=AKIAR7FXZINYPTKJO46C%2F20260501%2Fus-gov-west-1%2Fs3%2Faws4_request&X-Amz-Date=20260501T133716Z&X-Amz-Expires=30&X-Amz-SignedHeaders=host&X-Amz-Signature=ef4a0d10d181a03790a97d242b02a336b1f307df74f0fcccc7563ec2c5141f81",
        "http_status": 200,
        "status": "PASS",
        "url": "https://app.fac.gov/dissemination/report/pdf/2019-06-CENSUS-0000124840"
      },
      {
        "check_id": "link_check_591dd3eca9a1cefc",
        "content_type": "application/pdf",
        "error": "",
        "final_url": "https://s3-us-gov-west-1.amazonaws.com/cg-ac8bf271-4c6d-4ee0-bd36-1415b839a93c/singleauditreport/2019-06-CENSUS-0000124927.pdf?response-content-disposition=attachment%3Bfilename%3D2019-06-CENSUS-0000124927.pdf&X-Amz-Algorithm=AWS4-HMAC-SHA256&X-Amz-Credential=AKIAR7FXZINYPTKJO46C%2F20260501%2Fus-gov-west-1%2Fs3%2Faws4_request&X-Amz-Date=20260501T133717Z&X-Amz-Expires=30&X-Amz-SignedHeaders=host&X-Amz-Signature=d00e8b66a1e885cd9019c50e2af213330c557c4ed48f95601e6397b6b474ff0d",
        "http_status": 200,
        "status": "PASS",
        "url": "https://app.fac.gov/dissemination/report/pdf/2019-06-CENSUS-0000124927"
      },
      {
        "check_id": "link_check_a599aa40177bb6ad",
        "content_type": "application/pdf",
        "error": "",
        "final_url": "https://s3-us-gov-west-1.amazonaws.com/cg-ac8bf271-4c6d-4ee0-bd36-1415b839a93c/singleauditreport/2019-06-CENSUS-0000247998.pdf?response-content-disposition=attachment%3Bfilename%3D2019-06-CENSUS-0000247998.pdf&X-Amz-Algorithm=AWS4-HMAC-SHA256&X-Amz-Credential=AKIAR7FXZINYPTKJO46C%2F20260501%2Fus-gov-west-1%2Fs3%2Faws4_request&X-Amz-Date=20260501T133718Z&X-Amz-Expires=30&X-Amz-SignedHeaders=host&X-Amz-Signature=c9e4ecc424ff7bfe6d81caff9f776cb3056814abeafe32f35c69b053691950f4",
        "http_status": 200,
        "status": "PASS",
        "url": "https://app.fac.gov/dissemination/report/pdf/2019-06-CENSUS-0000247998"
      },
      {
        "check_id": "link_check_b33455a11a28c456",
        "content_type": "application/pdf",
        "error": "",
        "final_url": "https://s3-us-gov-west-1.amazonaws.com/cg-ac8bf271-4c6d-4ee0-bd36-1415b839a93c/singleauditreport/2019-06-CENSUS-0000249434.pdf?response-content-disposition=attachment%3Bfilename%3D2019-06-CENSUS-0000249434.pdf&X-Amz-Algorithm=AWS4-HMAC-SHA256&X-Amz-Credential=AKIAR7FXZINYPTKJO46C%2F20260501%2Fus-gov-west-1%2Fs3%2Faws4_request&X-Amz-Date=20260501T133719Z&X-Amz-Expires=30&X-Amz-SignedHeaders=host&X-Amz-Signature=3ea61347ed5a58bb9b9bb7c2479347fa01a95566851966838f8cecc4e76171c2",
        "http_status": 200,
        "status": "PASS",
        "url": "https://app.fac.gov/dissemination/report/pdf/2019-06-CENSUS-0000249434"
      },
      {
        "check_id": "link_check_bb63d4922aa3753f",
        "content_type": "application/pdf",
        "error": "",
        "final_url": "https://s3-us-gov-west-1.amazonaws.com/cg-ac8bf271-4c6d-4ee0-bd36-1415b839a93c/singleauditreport/2020-06-CENSUS-0000122774.pdf?response-content-disposition=attachment%3Bfilename%3D2020-06-CENSUS-0000122774.pdf&X-Amz-Algorithm=AWS4-HMAC-SHA256&X-Amz-Credential=AKIAR7FXZINYPTKJO46C%2F20260501%2Fus-gov-west-1%2Fs3%2Faws4_request&X-Amz-Date=20260501T133720Z&X-Amz-Expires=30&X-Amz-SignedHeaders=host&X-Amz-Signature=c8df2b60d9a0f5f34757290f46fafc1c65f9ca2210d7a60702b77476b2433f43",
        "http_status": 200,
        "status": "PASS",
        "url": "https://app.fac.gov/dissemination/report/pdf/2020-06-CENSUS-0000122774"
      }
    ],
    "created_at": "2026-05-01T13:37:21+00:00",
    "error_count": 0,
    "report_id": "link_integrity_614745fc2d81feee",
    "status": "PASS",
    "warning_count": 0
  },
  "link_repair": {
    "affected_evidence_refs": [
      "E02",
      "E04",
      "E12",
      "E13",
      "E14",
      "E15",
      "E18",
      "E19",
      "E20",
      "E40",
      "E41",
      "E42",
      "E43"
    ],
    "note": "Stale or renamed public URLs are repaired to working source pages before publication. Links are not removed as a substitute for repair.",
    "repaired_public_links": 26,
    "replacements": [
      {
        "new_url": "https://apps.irs.gov/pub/epostcard/990/xml/2024/index_2024.csv",
        "old_unlinked_reference": "apps.irs.gov/pub/epostcard/990/xml/2024/2024_TEOS_XML_04A.zip#2024_TEOS_XML_04A/202441109349300129_public.xml",
        "ref": "E02"
      },
      {
        "new_url": "https://apps.irs.gov/pub/epostcard/990/xml/2024/index_2024.csv",
        "old_unlinked_reference": "apps.irs.gov/pub/epostcard/990/xml/2024/2024_TEOS_XML_04A.zip#2024_TEOS_XML_04A/202441109349300129_public.xml",
        "ref": "E04"
      },
      {
        "new_url": "https://apps.irs.gov/pub/epostcard/990/xml/2025/index_2025.csv",
        "old_unlinked_reference": "apps.irs.gov/pub/epostcard/990/xml/2025/2025_TEOS_XML_04A.zip#202501089349300500_public.xml",
        "ref": "E04"
      },
      {
        "new_url": "https://apps.irs.gov/pub/epostcard/990/xml/2024/index_2024.csv",
        "old_unlinked_reference": "apps.irs.gov/pub/epostcard/990/xml/2024/2024_TEOS_XML_04A.zip#2024_TEOS_XML_04A/202400959349300030_public.xml",
        "ref": "E04"
      },
      {
        "new_url": "https://apps.irs.gov/pub/epostcard/990/xml/2025/index_2025.csv",
        "old_unlinked_reference": "apps.irs.gov/pub/epostcard/990/xml/2025/2025_TEOS_XML_04A.zip#202541049349301739_public.xml",
        "ref": "E04"
      },
      {
        "new_url": "https://apps.irs.gov/pub/epostcard/990/xml/2026/index_2026.csv",
        "old_unlinked_reference": "apps.irs.gov/pub/epostcard/990/xml/2026/2026_TEOS_XML_03A.zip#202620839349300647_public.xml",
        "ref": "E04"
      },
      {
        "new_url": "https://apps.irs.gov/pub/epostcard/990/xml/2024/index_2024.csv",
        "old_unlinked_reference": "apps.irs.gov/pub/epostcard/990/xml/2024/2024_TEOS_XML_04A.zip#2024_TEOS_XML_04A/202441109349300129_public.xml",
        "ref": "E12"
      },
      {
        "new_url": "https://apps.irs.gov/pub/epostcard/990/xml/2024/index_2024.csv",
        "old_unlinked_reference": "apps.irs.gov/pub/epostcard/990/xml/2024/2024_TEOS_XML_04A.zip#2024_TEOS_XML_04A/202441109349300129_public.xml",
        "ref": "E13"
      },
      {
        "new_url": "https://apps.irs.gov/pub/epostcard/990/xml/2024/index_2024.csv",
        "old_unlinked_reference": "apps.irs.gov/pub/epostcard/990/xml/2024/2024_TEOS_XML_04A.zip#2024_TEOS_XML_04A/202441109349300129_public.xml",
        "ref": "E14"
      },
      {
        "new_url": "https://apps.irs.gov/pub/epostcard/990/xml/2024/index_2024.csv",
        "old_unlinked_reference": "apps.irs.gov/pub/epostcard/990/xml/2024/2024_TEOS_XML_04A.zip#2024_TEOS_XML_04A/202441109349300129_public.xml",
        "ref": "E15"
      },
      {
        "new_url": "https://data.chhs.ca.gov/",
        "old_unlinked_reference": "data.chhs.ca.gov/api/3/action",
        "ref": "E18"
      },
      {
        "new_url": "https://lab.data.ca.gov/",
        "old_unlinked_reference": "data.ca.gov/api/3/action",
        "ref": "E18"
      },
      {
        "new_url": "https://lab.data.ca.gov/dataset/medication-assisted-treatment-in-medi-cal-for-opioid-use-disorders-by-county",
        "old_unlinked_reference": "data.chhs.ca.gov/dataset/medication-assisted-treatment-in-medi-cal-for-opioid-use-disorders-by-county",
        "ref": "E18"
      },
      {
        "new_url": "https://apps.irs.gov/pub/epostcard/990/xml/2024/index_2024.csv",
        "old_unlinked_reference": "apps.irs.gov/pub/epostcard/990/xml/2024/2024_TEOS_XML_04A.zip#2024_TEOS_XML_04A/202441109349300129_public.xml",
        "ref": "E19"
      },
      {
        "new_url": "https://apps.irs.gov/pub/epostcard/990/xml/2025/index_2025.csv",
        "old_unlinked_reference": "apps.irs.gov/pub/epostcard/990/xml/2025/2025_TEOS_XML_04A.zip#202501089349300500_public.xml",
        "ref": "E19"
      },
      {
        "new_url": "https://apps.irs.gov/pub/epostcard/990/xml/2024/index_2024.csv",
        "old_unlinked_reference": "apps.irs.gov/pub/epostcard/990/xml/2024/2024_TEOS_XML_04A.zip#2024_TEOS_XML_04A/202400959349300030_public.xml",
        "ref": "E19"
      },
      {
        "new_url": "https://apps.irs.gov/pub/epostcard/990/xml/2025/index_2025.csv",
        "old_unlinked_reference": "apps.irs.gov/pub/epostcard/990/xml/2025/2025_TEOS_XML_04A.zip#202541049349301739_public.xml",
        "ref": "E19"
      },
      {
        "new_url": "https://apps.irs.gov/pub/epostcard/990/xml/2026/index_2026.csv",
        "old_unlinked_reference": "apps.irs.gov/pub/epostcard/990/xml/2026/2026_TEOS_XML_03A.zip#202620839349300647_public.xml",
        "ref": "E19"
      },
      {
        "new_url": "https://www.tarzanatc.org/treatment-news/",
        "old_unlinked_reference": "www.tarzanatc.org/news-events/",
        "ref": "E20"
      },
      {
        "new_url": "https://socialmodelrecovery.org/",
        "old_unlinked_reference": "socialmodelrecovery.org/annual-report/",
        "ref": "E20"
      },
      {
        "new_url": "https://socialmodelrecovery.org/services/",
        "old_unlinked_reference": "www.socialmodelrecovery.org/about-us/",
        "ref": "E20"
      },
      {
        "new_url": "https://socialmodelrecovery.org/services/",
        "old_unlinked_reference": "www.socialmodelrecovery.org/programs/",
        "ref": "E20"
      },
      {
        "new_url": "https://apps.irs.gov/pub/epostcard/990/xml/2025/index_2025.csv",
        "old_unlinked_reference": "apps.irs.gov/pub/epostcard/990/xml/2025/2025_TEOS_XML_04A.zip#202501089349300500_public.xml",
        "ref": "E40"
      },
      {
        "new_url": "https://apps.irs.gov/pub/epostcard/990/xml/2024/index_2024.csv",
        "old_unlinked_reference": "apps.irs.gov/pub/epostcard/990/xml/2024/2024_TEOS_XML_04A.zip#2024_TEOS_XML_04A/202400959349300030_public.xml",
        "ref": "E41"
      },
      {
        "new_url": "https://apps.irs.gov/pub/epostcard/990/xml/2025/index_2025.csv",
        "old_unlinked_reference": "apps.irs.gov/pub/epostcard/990/xml/2025/2025_TEOS_XML_04A.zip#202541049349301739_public.xml",
        "ref": "E42"
      },
      {
        "new_url": "https://apps.irs.gov/pub/epostcard/990/xml/2026/index_2026.csv",
        "old_unlinked_reference": "apps.irs.gov/pub/epostcard/990/xml/2026/2026_TEOS_XML_03A.zip#202620839349300647_public.xml",
        "ref": "E43"
      }
    ]
  },
  "public_link_access": {
    "checked_url_count": 78,
    "complete": true,
    "error_count": 0,
    "evidence_rows_without_verified_public_link": 0,
    "note": "Public link access means every published evidence row has a verified browser-openable URL or a visible source-access note. It is not the same as raw-source or completion-guard access.",
    "status": "PASS",
    "warning_count": 0
  },
  "publication_context": {
    "completion_guard_blocker_count": 0,
    "completion_guard_hit_count": 0,
    "completion_guard_missing_required": [],
    "completion_guard_status": "not computed",
    "completion_guard_total": 0,
    "evidence_count": 60,
    "human_decision": "PENDING",
    "public_link_access": {
      "checked_url_count": 78,
      "complete": true,
      "error_count": 0,
      "evidence_rows_without_verified_public_link": 0,
      "note": "Public link access means every published evidence row has a verified browser-openable URL or a visible source-access note. It is not the same as raw-source or completion-guard access.",
      "status": "PASS",
      "warning_count": 0
    },
    "public_link_checked_count": 78,
    "public_link_error_count": 0,
    "public_link_status": "PASS",
    "publication_confidence": "not computed",
    "review_priority": 51.52,
    "risk_severity": "not computed",
    "run_label": "live_ca_recovery_ngos_2026_04_24",
    "source_access": {
      "affected_evidence_refs": [],
      "complete": false,
      "completion_guard_access_complete": false,
      "completion_guard_blocker_count": 0,
      "completion_guard_missing_required": [],
      "completion_guard_status": "not computed",
      "items": [],
      "note": "Source access combines public-link access with completion-guard access. Verified links do not clear unresolved acquisition blockers, and missing source access is never treated as completion.",
      "partial_items": [],
      "partial_source_access_issue_count": 0,
      "public_link_access_complete": true,
      "source_access_required_count": 0
    },
    "source_completeness": "not computed",
    "verified_linked_evidence_count": 60,
    "workflow_state": "AWAITING_HUMAN_REVIEW"
  },
  "publication_id": "publication_7b14edf3e04bc12a",
  "safety": {
    "checked_files": [
      "case_dossier.md",
      "index.html",
      "source_ledger.json"
    ],
    "errors": [],
    "evidence_refs_checked": 60,
    "passed": true,
    "source_access": {
      "affected_evidence_refs": [],
      "complete": false,
      "completion_guard_access_complete": false,
      "completion_guard_blocker_count": 0,
      "completion_guard_missing_required": [],
      "completion_guard_status": "not computed",
      "items": [],
      "note": "Source access combines public-link access with completion-guard access. Verified links do not clear unresolved acquisition blockers, and missing source access is never treated as completion.",
      "partial_items": [],
      "partial_source_access_issue_count": 0,
      "public_link_access_complete": true,
      "source_access_required_count": 0
    },
    "source_ledger_entries": 60,
    "warnings": []
  },
  "sentinel_decision": "DOWNGRADE_FOR_REVIEW",
  "source_access": {
    "affected_evidence_refs": [],
    "complete": false,
    "completion_guard_access_complete": false,
    "completion_guard_blocker_count": 0,
    "completion_guard_missing_required": [],
    "completion_guard_status": "not computed",
    "items": [],
    "note": "Source access combines public-link access with completion-guard access. Verified links do not clear unresolved acquisition blockers, and missing source access is never treated as completion.",
    "partial_items": [],
    "partial_source_access_issue_count": 0,
    "public_link_access_complete": true,
    "source_access_required_count": 0
  },
  "source_run_label": "live_ca_recovery_ngos_2026_04_24",
  "unverified_link_access": {
    "affected_evidence_refs": [],
    "items": [],
    "note": "All public source URLs passed link verification after deterministic repairs.",
    "unverified_public_links": 0
  }
}
